fenicsx_pulse/__init__.py
fenicsx_pulse-0.5.1.dist-info/licenses/LICENSE
pulse/__init__.py
pulse/_types.py
pulse/active_model.py
pulse/active_stress.py
pulse/boundary_conditions.py
pulse/cardiac_model.py
pulse/cli.py
pulse/compressibility.py
pulse/exceptions.py
pulse/functions.py
pulse/geometry.py
pulse/invariants.py
pulse/kinematics.py
pulse/material_model.py
pulse/problem.py
pulse/units.py
pulse/unloading.py
pulse/utils.py
pulse/viscoelasticity.py
pulse/material_models/__init__.py
pulse/material_models/guccione.py
pulse/material_models/holzapfelogden.py
pulse/material_models/neo_hookean.py
pulse/material_models/saint_venant_kirchhoff.py
pulse/material_models/usyk.py
fenicsx_pulse-0.5.1.dist-info/METADATA
fenicsx_pulse-0.5.1.dist-info/WHEEL
fenicsx_pulse-0.5.1.dist-info/entry_points.txt
fenicsx_pulse-0.5.1.dist-info/top_level.txt
fenicsx_pulse-0.5.1.dist-info/RECORD
