Metadata-Version: 2.4
Name: fenicsx-pulse
Version: 0.5.1
Summary: Next generation cardiac mechanics solver based on FEniCSx
Author-email: Henrik Finsberg <henriknf@simula.no>
License-Expression: MIT
Requires-Python: >=3.10.0
License-File: LICENSE
Requires-Dist: fenics-dolfinx
Requires-Dist: pint
Requires-Dist: scifem
Requires-Dist: rich
Requires-Dist: rich-argparse
Provides-Extra: test
Requires-Dist: pytest; extra == "test"
Requires-Dist: pytest-cov; extra == "test"
Requires-Dist: cardiac-geometriesx; extra == "test"
Provides-Extra: dev
Requires-Dist: pdbpp; extra == "dev"
Requires-Dist: ipython; extra == "dev"
Requires-Dist: bump2version; extra == "dev"
Requires-Dist: pre-commit; extra == "dev"
Provides-Extra: demo
Requires-Dist: cardiac-geometriesx; extra == "demo"
Requires-Dist: fenicsx-ldrb; extra == "demo"
Requires-Dist: circulation; extra == "demo"
Requires-Dist: gotranx; extra == "demo"
Requires-Dist: adios4dolfinx; extra == "demo"
Requires-Dist: scipy; extra == "demo"
Requires-Dist: ukb-atlas; extra == "demo"
Provides-Extra: docs
Requires-Dist: sphinx; extra == "docs"
Requires-Dist: jupytext; extra == "docs"
Requires-Dist: jupyter; extra == "docs"
Requires-Dist: pyvista[all]>=0.45.0; extra == "docs"
Requires-Dist: vtk>=9.5.0; extra == "docs"
Requires-Dist: trame-vuetify; extra == "docs"
Requires-Dist: ipywidgets; extra == "docs"
Requires-Dist: fenicsx-pulse[demo]; extra == "docs"
Requires-Dist: sphinx-codeautolink; extra == "docs"
Requires-Dist: sphinxcontrib-bibtex; extra == "docs"
Requires-Dist: sphinx-copybutton; extra == "docs"
Requires-Dist: sphinx-codeautolink; extra == "docs"
Requires-Dist: sphinx-togglebutton; extra == "docs"
Requires-Dist: sphinx-comments; extra == "docs"
Requires-Dist: sphinx-external-toc; extra == "docs"
Requires-Dist: linkify-it-py; extra == "docs"
Requires-Dist: sphinx-design; extra == "docs"
Requires-Dist: sphinx-book-theme; extra == "docs"
Requires-Dist: myst-nb; extra == "docs"
Requires-Dist: sphinx-multitoc-numbering; extra == "docs"
Provides-Extra: benchmark
Requires-Dist: pytest-codspeed; extra == "benchmark"
Requires-Dist: fenicsx-pulse[test]; extra == "benchmark"
Provides-Extra: all
Requires-Dist: fenicsx-pulse[test]; extra == "all"
Requires-Dist: fenicsx-pulse[docs]; extra == "all"
Requires-Dist: fenicsx-pulse[dev]; extra == "all"
Requires-Dist: fenicsx-pulse[demo]; extra == "all"
Dynamic: license-file
